korean_glue/__init__.py
korean_glue/__main__.py
korean_glue/dictionary.py
korean_glue/engine.py
korean_glue/exceptions.py
korean_glue/py.typed
korean_glue/rules.py
korean_glue/integrations/__init__.py
korean_glue/integrations/django_tags.py
korean_glue/integrations/jinja_filters.py
korean_glue-0.1.4.dist-info/METADATA
korean_glue-0.1.4.dist-info/WHEEL
korean_glue-0.1.4.dist-info/entry_points.txt
korean_glue-0.1.4.dist-info/licenses/LICENSE
korean_glue-0.1.4.dist-info/RECORD
