Metadata-Version: 2.4
Name: korean_glue
Version: 0.1.4
Summary: A modern Python library for Korean josa processing with dictionary support and framework integrations.
Author-email: woojing <woojing.seok@gmail.com>
License: MIT
License-File: LICENSE
Classifier: Development Status :: 4 - Beta
Classifier: Intended Audience :: Developers
Classifier: License :: OSI Approved :: MIT License
Classifier: Natural Language :: Korean
Classifier: Operating System :: OS Independent
Classifier: Programming Language :: Python :: 3
Classifier: Programming Language :: Python :: 3 :: Only
Classifier: Programming Language :: Python :: 3.10
Classifier: Programming Language :: Python :: 3.11
Classifier: Programming Language :: Python :: 3.12
Classifier: Programming Language :: Python :: 3.13
Classifier: Topic :: Software Development :: Libraries
Classifier: Topic :: Text Processing :: Linguistic
Requires-Python: >=3.10
Provides-Extra: dev
Requires-Dist: black; extra == 'dev'
Requires-Dist: bump-my-version; extra == 'dev'
Requires-Dist: django!=5.0.*,<5.3,>=4.2; extra == 'dev'
Requires-Dist: flake8; extra == 'dev'
Requires-Dist: jinja2<3.2,>=3.1; extra == 'dev'
Requires-Dist: mypy; extra == 'dev'
Requires-Dist: pre-commit; extra == 'dev'
Requires-Dist: pytest; extra == 'dev'
Requires-Dist: pytest-cov; extra == 'dev'
Requires-Dist: tox; extra == 'dev'
Requires-Dist: tox-uv; extra == 'dev'
